oatdb/__init__.py
oatdb-0.4.5.dist-info/METADATA
oatdb-0.4.5.dist-info/WHEEL
oatdb-0.4.5.dist-info/RECORD
