Metadata-Version: 2.1
Name: oatdb
Version: 0.4.5
Summary: Python client for OAT (Optimization and Analysis Tooling) database
License: MIT
Keywords: optimization,constraint-solving,database
Author: Rikard Olsson
Requires-Python: >=3.10,<4.0
Classifier: Development Status :: 3 - Alpha
Classifier: Intended Audience :: Developers
Classifier: License :: OSI Approved :: MIT License
Classifier: Programming Language :: Python :: 3
Classifier: Programming Language :: Python :: 3.10
Classifier: Programming Language :: Python :: 3.11
Classifier: Programming Language :: Python :: 3.12
Classifier: Programming Language :: Python :: 3.13
Requires-Dist: more-itertools (>=10.8.0,<11.0.0)
Requires-Dist: pldag (>=0.10.17,<0.11.0)
Requires-Dist: requests (>=2.31.0,<3.0.0)
